easytest/__init__.py
easytest/case.py
easytest/loader.py
easytest/main.py
easytest/producer.py
easytest/result.py
easytest/runner.py
easytest/utils.py
easytest/common/__init__.py
easytest/common/db_handler.py
easytest/common/log_handler.py
easytest/common/test_data_handler.py
http_easytest-1.1.2.dist-info/LICENSE
http_easytest-1.1.2.dist-info/METADATA
http_easytest-1.1.2.dist-info/WHEEL
http_easytest-1.1.2.dist-info/entry_points.txt
http_easytest-1.1.2.dist-info/top_level.txt
http_easytest-1.1.2.dist-info/RECORD
